shipy/__init__.py
shipy/_log.py
shipy/app.py
shipy/auth.py
shipy/cli.py
shipy/csrf.py
shipy/flash.py
shipy/forms.py
shipy/render.py
shipy/session.py
shipy/sql.py
shipy_web-0.3.3.dist-info/METADATA
shipy_web-0.3.3.dist-info/WHEEL
shipy_web-0.3.3.dist-info/entry_points.txt
shipy_web-0.3.3.dist-info/licenses/LICENSE
shipy_web-0.3.3.dist-info/RECORD
