Metadata-Version: 2.4
Name: shipy-web
Version: 0.3.3
Summary: The opinionated Indie Maker Python web framework for shipping MVPs stupid-fast.
Project-URL: Homepage, https://github.com/yourname/shipy
Project-URL: Issues, https://github.com/yourname/shipy/issues
Author-email: Rafael <you@example.com>
License: MIT
License-File: LICENSE
Keywords: framework,jinja2,mvp,sqlite,web
Classifier: Framework :: AsyncIO
Classifier: Intended Audience :: Developers
Classifier: License :: OSI Approved :: MIT License
Classifier: Programming Language :: Python :: 3
Classifier: Topic :: Internet :: WWW/HTTP
Requires-Python: >=3.11
Requires-Dist: jinja2>=3.1
Requires-Dist: uvicorn>=0.30
Provides-Extra: bcrypt
Requires-Dist: bcrypt>=4.0; extra == 'bcrypt'
Provides-Extra: test
Requires-Dist: anyio>=4.0; extra == 'test'
Requires-Dist: httpx>=0.27; extra == 'test'
Requires-Dist: pytest>=8.0; extra == 'test'
